{"id":189,"photo":"103955.jpg","web_name":"Sterling","event_explain":[["Minutes played",0,0]],"fixture_history":{"all":[["10 Aug 20:00",1,"WBA(A) 3-0",73,0,0,1,0,0,0,0,0,0,0,0,23,8,0,90,3],["16 Aug 16:00",2,"CHE(H) 3-0",78,0,0,1,0,0,0,0,0,0,0,0,13,10,-50069,90,3],["23 Aug 16:00",3,"EVE(A) 2-0",75,0,1,1,0,0,0,0,0,0,0,0,27,17,-165410,89,6],["29 Aug 15:00",4,"WAT(H) 2-0",88,1,0,1,0,0,0,0,0,0,0,1,41,34,-47334,89,9],["12 Sep 15:00",5,"CRY(A) 1-0",0,0,0,0,0,0,0,0,0,0,0,0,0,0,38016,89,0],["19 Sep 17:30",6,"WHU(H) 1-2",65,0,0,0,2,0,0,0,0,0,0,0,3,8,-26123,89,2],["26 Sep 12:45",7,"TOT(A) 1-4",90,0,0,0,4,0,0,0,0,0,0,0,16,11,-39230,89,2],["03 Oct 15:00",8,"NEW(H) 6-1",45,0,0,0,1,0,0,0,0,0,0,0,8,-1,-17817,89,1],["17 Oct 15:00",9,"BOU(H) 5-1",77,3,0,0,1,0,0,0,0,0,0,2,60,57,-67434,88,19],["25 Oct 14:05",10,"MUN(A) 0-0",54,0,0,0,0,0,0,0,0,0,0,0,4,1,76009,89,1],["31 Oct 15:00",11,"NOR(H) 2-1",37,0,1,0,1,0,0,0,0,0,0,0,6,11,-3692,89,4],["08 Nov 13:30",12,"AVL(A) 0-0",83,0,0,1,0,0,0,0,0,0,0,0,11,4,29952,89,3],["21 Nov 17:30",13,"LIV(H) 1-4",90,0,0,0,4,0,0,0,0,0,0,0,5,7,5114,89,2],["28 Nov 15:00",14,"SOU(H) 3-1",74,0,1,0,1,0,0,0,0,0,0,0,23,22,-22588,89,5],["05 Dec 12:45",15,"STK(A) 0-2",90,0,0,0,2,0,0,0,0,0,0,0,7,8,267,89,2],["12 Dec 15:00",16,"SWA(H) 2-1",45,0,0,0,0,0,0,0,0,0,0,0,9,8,23244,89,1],["21 Dec 20:00",17,"ARS(A) 1-2",45,0,0,0,0,0,0,0,0,0,0,0,9,-1,-46838,89,1],["26 Dec 15:00",18,"SUN(H) 4-1",90,1,0,0,1,0,0,0,1,0,0,0,34,19,-28009,89,6],["29 Dec 19:45",19,"LEI(A) 0-0",88,0,0,1,0,0,0,0,0,0,0,0,27,5,-8466,88,3],["02 Jan 17:30",20,"WAT(A) 2-1",59,0,0,0,1,0,0,0,0,0,0,0,7,5,-14225,88,1],["13 Jan 19:45",21,"EVE(H) 0-0",90,0,0,1,0,0,0,0,0,0,0,0,11,21,-26437,87,3],["16 Jan 15:00",22,"CRY(H) 4-0",0,0,0,0,0,0,0,0,0,0,0,0,0,0,-13064,87,0],["23 Jan 17:30",23,"WHU(A) 2-2",24,0,0,0,0,0,0,0,0,0,0,0,2,0,-24986,86,1],["02 Feb 19:45",24,"SUN(A) 1-0",15,0,0,0,0,0,0,0,0,0,0,0,2,0,-6248,86,1],["06 Feb 12:45",25,"LEI(H) 1-3",90,0,0,0,3,0,0,0,0,0,0,0,1,14,-14300,86,2],["14 Feb 16:15",26,"TOT(H) 1-2",90,0,0,0,2,0,0,0,0,0,0,0,8,12,-13222,85,2],["02 Mar 20:00",28,"LIV(A) 0-3",45,0,0,0,2,0,0,0,0,0,0,0,-1,5,-1101,85,1],["05 Mar 15:00",29,"AVL(H) 4-0",29,1,0,0,0,0,0,0,0,0,0,0,26,20,13818,85,6],["12 Mar 12:45",30,"NOR(A) 0-0",33,0,0,0,0,0,0,0,0,0,0,0,3,-2,42608,85,1],["20 Mar 16:00",31,"MUN(H) 0-1",25,0,0,0,1,0,0,0,0,0,0,0,1,3,-27461,86,1],["02 Apr 15:00",32,"BOU(A) 4-0",0,0,0,0,0,0,0,0,0,0,0,0,0,0,-36255,86,0],["09 Apr 17:30",33,"WBA(H) 2-1",0,0,0,0,0,0,0,0,0,0,0,0,0,0,-10061,85,0],["16 Apr 17:30",34,"CHE(A) 3-0",0,0,0,0,0,0,0,0,0,0,0,0,0,0,-4688,85,0],["19 Apr 19:45",34,"NEW(A) 1-1",23,0,0,0,0,0,0,0,0,0,0,0,2,7,-4688,85,1],["23 Apr 12:45",35,"STK(H) 4-0",0,0,0,0,0,0,0,0,0,0,0,0,0,0,-1196,85,0],["01 May 16:30",36,"SOU(A) 2-4",90,0,0,0,4,0,0,0,0,0,0,0,11,9,-488,85,2],["08 May 16:00",37,"ARS(H) 2-2",20,0,0,0,0,0,0,0,0,0,0,0,1,2,-708,85,1],["15 May 15:00",38,"SWA(A) 1-1",0,0,0,0,0,0,0,0,0,0,0,0,0,0,-195,85,0]],"summary":[[36,"SOU (A)",2],[37,"ARS (H)",1],[38,"SWA (A)",0]]},"season_history":[["2011/12",30,0,0,0,0,0,0,0,0,0,0,0,2,0,46,3],["2012/13",1748,2,6,6,24,0,0,0,1,0,0,7,272,0,46,82],["2013/14",2219,9,7,6,31,0,0,0,3,0,0,7,647,125,64,132],["2014/15",3047,7,10,13,39,0,0,0,5,0,0,16,673,513,83,158]],"fixtures":{"all":[],"summary":[]},"event_total":0,"type_name":"Midfielder","team_name":"Man City","selected_by":"5.8","total_points":96,"current_fixture":"Swansea (A)","next_fixture":"","team_code":43,"news":"","team_id":9,"status":"a","code":103955,"first_name":"Raheem","second_name":"Sterling","now_cost":85,"chance_of_playing_this_round":100,"chance_of_playing_next_round":100,"value_form":"0.1","value_season":"11.3","cost_change_start":-5,"cost_change_event":0,"cost_change_start_fall":5,"cost_change_event_fall":0,"in_dreamteam":false,"dreamteam_count":1,"selected_by_percent":"5.8","form":"0.8","transfers_out":1013276,"transfers_in":510676,"transfers_out_event":0,"transfers_in_event":0,"loans_in":0,"loans_out":0,"loaned_in":0,"loaned_out":0,"event_points":0,"points_per_game":"3.1","ep_this":"0.8","ep_next":"0.8","special":false,"minutes":1920,"goals_scored":6,"assists":3,"clean_sheets":7,"goals_conceded":30,"own_goals":0,"penalties_saved":0,"penalties_missed":0,"yellow_cards":1,"red_cards":0,"saves":0,"bonus":3,"ea_index":400,"bps":324,"element_type":3,"team":9}