{"id":511,"photo":"67527.jpg","web_name":"Nyom","event_explain":[["Minutes played",0,0]],"fixture_history":{"all":[["08 Aug 15:00",1,"EVE(A) 2-2",90,0,0,0,2,0,0,0,0,0,0,0,8,22,0,45,1],["15 Aug 15:00",2,"WBA(H) 0-0",90,0,0,1,0,0,0,0,1,0,0,0,16,20,-44,45,5],["23 Aug 16:00",3,"SOU(H) 0-0",90,0,0,1,0,0,0,0,0,0,0,3,6,33,282,45,9],["29 Aug 15:00",4,"MCI(A) 0-2",90,0,0,0,2,0,0,0,1,0,0,0,4,14,4807,45,0],["12 Sep 15:00",5,"SWA(H) 1-0",90,0,0,1,0,0,0,0,0,0,0,1,18,26,1577,45,7],["19 Sep 15:00",6,"NEW(A) 2-1",90,0,0,0,1,0,0,0,0,0,0,0,15,20,18806,45,2],["27 Sep 16:00",7,"CRY(H) 0-1",74,0,0,0,1,0,0,0,0,0,0,0,7,11,5893,45,2],["03 Oct 15:00",8,"BOU(A) 1-1",70,0,0,0,1,0,0,0,0,0,0,0,9,8,11295,45,2],["17 Oct 17:30",9,"ARS(H) 0-3",68,0,0,0,2,0,0,0,1,0,0,0,5,13,4766,45,0],["24 Oct 15:00",10,"STK(A) 2-0",90,0,0,1,0,0,0,0,0,0,0,2,17,30,1545,45,8],["31 Oct 15:00",11,"WHU(H) 2-0",90,0,0,1,0,0,0,0,1,0,0,0,15,17,23172,45,5],["07 Nov 15:00",12,"LEI(A) 1-2",75,0,0,0,2,0,0,0,0,0,0,0,0,16,33135,46,1],["21 Nov 12:45",13,"MUN(H) 1-2",68,0,0,0,1,0,0,0,0,0,0,0,4,9,2615,46,2],["28 Nov 15:00",14,"AVL(A) 3-2",90,0,0,0,2,0,0,0,0,0,0,0,16,16,9688,46,1],["05 Dec 15:00",15,"NOR(H) 2-0",90,0,0,1,0,0,0,0,0,0,0,0,17,25,4399,46,6],["12 Dec 15:00",16,"SUN(A) 1-0",90,0,1,1,0,0,0,0,0,0,0,3,25,47,6306,46,12],["20 Dec 13:30",17,"LIV(H) 3-0",90,0,0,1,0,0,0,0,0,0,0,0,14,18,29149,46,6],["26 Dec 15:00",18,"CHE(A) 2-2",90,0,0,0,2,0,0,0,0,0,0,0,7,11,40954,47,1],["28 Dec 15:00",19,"TOT(H) 1-2",23,0,0,0,1,0,0,0,0,0,0,0,1,6,11531,47,1],["02 Jan 17:30",20,"MCI(H) 1-2",90,0,0,0,2,0,0,0,1,0,0,0,5,12,4985,47,0],["13 Jan 19:45",21,"SOU(A) 0-2",67,0,0,0,1,0,0,0,0,0,0,0,3,12,5542,47,2],["18 Jan 20:00",22,"SWA(A) 0-1",73,0,0,0,1,0,0,0,1,0,0,0,1,8,2350,47,1],["23 Jan 15:00",23,"NEW(H) 2-1",2,0,0,0,0,0,0,0,0,0,0,0,0,3,-7534,47,1],["03 Feb 19:45",24,"CHE(H) 0-0",23,0,0,0,0,0,0,0,0,0,0,0,2,9,-18073,47,1],["06 Feb 15:00",25,"TOT(A) 0-1",90,0,0,0,1,0,0,0,0,0,0,0,8,26,-13500,47,2],["13 Feb 15:00",26,"CRY(A) 2-1",90,0,0,0,1,0,0,0,0,0,0,0,14,10,-11963,47,2],["27 Feb 15:00",27,"BOU(H) 0-0",0,0,0,0,0,0,0,0,0,0,0,0,0,0,-4619,47,0],["02 Mar 20:00",28,"MUN(A) 0-1",90,0,0,0,1,0,0,0,0,0,0,0,6,20,-10193,46,2],["05 Mar 17:30",29,"LEI(H) 0-1",81,0,0,0,1,0,0,0,0,0,0,0,6,15,-8525,46,2],["19 Mar 15:00",31,"STK(H) 1-2",90,0,0,0,2,0,0,0,1,0,0,0,4,11,-2167,45,0],["02 Apr 15:00",32,"ARS(A) 0-4",90,0,0,0,4,0,0,0,1,0,0,0,5,13,-5511,45,-1],["09 Apr 15:00",33,"EVE(H) 1-1",0,0,0,0,0,0,0,0,0,0,0,0,0,0,-6124,45,0],["16 Apr 15:00",34,"WBA(A) 1-0",90,0,0,1,0,0,0,0,0,0,0,0,15,16,-6033,44,6],["20 Apr 19:45",34,"WHU(A) 1-3",0,0,0,0,0,0,0,0,0,0,0,0,0,0,-6033,44,0],["30 Apr 15:00",36,"AVL(H) 3-2",0,0,0,0,0,0,0,0,0,0,0,0,0,0,3159,44,0],["08 May 16:00",37,"LIV(A) 0-2",0,0,0,0,0,0,0,0,0,0,0,0,0,0,-1930,44,0],["11 May 19:45",37,"NOR(A) 2-4",45,0,0,0,3,0,0,0,0,0,0,0,2,2,-1930,44,0],["15 May 15:00",38,"SUN(H) 2-2",0,0,0,0,0,0,0,0,0,0,0,0,0,0,-2001,44,0]],"summary":[[37,"LIV (A)",0],[37,"NOR (A)",0],[38,"SUN (H)",0]]},"season_history":[],"fixtures":{"all":[],"summary":[]},"event_total":0,"type_name":"Defender","team_name":"Watford","selected_by":"3.7","total_points":89,"current_fixture":"Sunderland (H)","next_fixture":"","team_code":57,"news":"","team_id":18,"status":"a","code":67527,"first_name":"Allan-Roméo","second_name":"Nyom","now_cost":44,"chance_of_playing_this_round":100,"chance_of_playing_next_round":100,"value_form":"0.0","value_season":"20.2","cost_change_start":-1,"cost_change_event":0,"cost_change_start_fall":1,"cost_change_event_fall":0,"in_dreamteam":false,"dreamteam_count":2,"selected_by_percent":"3.7","form":"0.0","transfers_out":227490,"transfers_in":337172,"transfers_out_event":0,"transfers_in_event":0,"loans_in":0,"loans_out":0,"loaned_in":0,"loaned_out":0,"event_points":0,"points_per_game":"2.8","ep_this":"0.0","ep_next":"1.2","special":false,"minutes":2469,"goals_scored":0,"assists":1,"clean_sheets":9,"goals_conceded":34,"own_goals":0,"penalties_saved":0,"penalties_missed":0,"yellow_cards":8,"red_cards":0,"saves":0,"bonus":9,"ea_index":275,"bps":519,"element_type":2,"team":18}